pykicadlib/__init__.py
pykicadlib/config.py
pykicadlib/version.py
pykicadlib/symbol/__init__.py
pykicadlib/symbol/elements.py
pykicadlib/symbol/types.py
scripts/__init__.py
scripts/eagle2kicad.py
scripts/footprint.py
scripts/symbols.py
scripts/tables.py
test/__init__.py
test/symbol/__init__.py
test/symbol/test_elements.py
test/symbol/test_from_str.py
test/symbol/test_types.py
pykicadlib-0.0.1.dist-info/LICENSE
pykicadlib-0.0.1.dist-info/METADATA
pykicadlib-0.0.1.dist-info/WHEEL
pykicadlib-0.0.1.dist-info/entry_points.txt
pykicadlib-0.0.1.dist-info/top_level.txt
pykicadlib-0.0.1.dist-info/RECORD
