Metadata-Version: 2.1
Name: pykicadlib
Version: 0.0.1
Summary: Python KiCAD library parser/generator
Home-page: https://code.fueldner.net/opensource/pykicadlib
Author: Benjamin Füldner
Author-email: benjamin@fueldner.net
License: MIT
Project-URL: Source, https://github.com/bfueldner/pykicadlib
Project-URL: Bug Reports, https://github.com/bfueldner/pykicadlib/issues
Keywords: KiCAD symbol footprint device PCB schematic
Platform: UNKNOWN
Classifier: Development Status :: 3 - Alpha
Classifier: Intended Audience :: Developers
Classifier: License :: OSI Approved :: MIT License
Classifier: Operating System :: OS Independent
Classifier: Programming Language :: Python :: 3
Classifier: Programming Language :: Python :: 3.5
Classifier: Programming Language :: Python :: 3.6
Classifier: Programming Language :: Python :: 3.7
Classifier: Topic :: System :: Hardware
Classifier: Topic :: Software Development
Classifier: Topic :: Software Development :: Embedded Systems
Classifier: Topic :: Scientific/Engineering :: Electronic Design Automation (EDA)
Classifier: Topic :: Home Automation
Requires-Python: >=3.5
